octosessionviewer/__init__.py
octosessionviewer/__main__.py
octosessionviewer/_version.py
octosessionviewer/session.py
octosessionviewer/common/__init__.py
octosessionviewer/common/clientconfig.py
octosessionviewer/common/credential.py
octosessionviewer/common/proxy.py
octosessionviewer/common/target.py
octosessionviewer-0.0.1.dist-info/METADATA
octosessionviewer-0.0.1.dist-info/WHEEL
octosessionviewer-0.0.1.dist-info/entry_points.txt
octosessionviewer-0.0.1.dist-info/top_level.txt
octosessionviewer-0.0.1.dist-info/zip-safe
octosessionviewer-0.0.1.dist-info/RECORD
