Metadata-Version: 2.1
Name: octosessionviewer
Version: 0.0.1
Home-page: https://github.com/octopwn/octosessionviewer
Author: Tamas Jos
Author-email: info@octopwn.com
Classifier: Programming Language :: Python :: 3.6
Classifier: Operating System :: OS Independent
Requires-Python: >=3.9
Requires-Dist: toml
Requires-Dist: cryptography
